LICENSE.txt
MANIFEST.in
README.rst
setup.py
openrtb/__init__.py
openrtb/base.py
openrtb/constants.py
openrtb/iab.py
openrtb/macros.py
openrtb/mobile.py
openrtb/request.py
openrtb/response.py
openrtb.egg-info/PKG-INFO
openrtb.egg-info/SOURCES.txt
openrtb.egg-info/dependency_links.txt
openrtb.egg-info/requires.txt
openrtb.egg-info/top_level.txt