Metadata-Version: 1.1
Name: openrtb
Version: 0.2.0
Summary: A set of classes implementing OpenRTB 2.2 and OpenRTB Mobile specifications
Home-page: https://github.com/anossov/openrtb
Author: Pavel Anossov
Author-email: anossov@gmail.com
License: BSD
Platform: UNKNOWN
Classifier: Development Status :: 4 - Beta
Classifier: Programming Language :: Python :: 2.7
Classifier: Programming Language :: Python :: 3.5
Classifier: Intended Audience :: Developers
Classifier: License :: OSI Approved :: BSD License
Classifier: Topic :: Software Development :: Libraries
